<?xml version='1.0' encoding='UTF-8'?>
<maecPackage:MAEC_Package 
	xmlns:cyboxCommon="http://cybox.mitre.org/common-2"
	xmlns:cybox="http://cybox.mitre.org/cybox-2"
	xmlns:cyboxVocabs="http://cybox.mitre.org/default_vocabularies-2"
	xmlns:FileObj="http://cybox.mitre.org/objects#FileObject-2"
	xmlns:example="http://example.com/"
	xmlns:maecBundle="http://maec.mitre.org/XMLSchema/maec-bundle-4"
	xmlns:maecPackage="http://maec.mitre.org/XMLSchema/maec-package-2"
	xmlns:maecVocabs="http://maec.mitre.org/default_vocabularies-1"
	xmlns:xsi="http://www.w3.org/2001/XMLSchema-instance"
	xsi:schemaLocation="http://cybox.mitre.org/common-2 http://cybox.mitre.org/XMLSchema/common/2.1/cybox_common.xsd http://cybox.mitre.org/cybox-2 http://cybox.mitre.org/XMLSchema/core/2.1/cybox_core.xsd http://cybox.mitre.org/default_vocabularies-2 http://cybox.mitre.org/XMLSchema/default_vocabularies/2.1/cybox_default_vocabularies.xsd http://cybox.mitre.org/objects#FileObject-2 http://cybox.mitre.org/XMLSchema/objects/File/2.1/File_Object.xsd http://maec.mitre.org/XMLSchema/maec-bundle-4 http://maec.mitre.org/language/version4.1/maec_bundle_schema.xsd http://maec.mitre.org/XMLSchema/maec-package-2 http://maec.mitre.org/language/version4.1/maec_package_schema.xsd http://maec.mitre.org/default_vocabularies-1 http://maec.mitre.org/language/version4.1/maec_default_vocabularies.xsd" id="example:package-ea077af0-5b49-40ff-bd45-cf3303decdb8" schema_version="2.1">
    <maecPackage:Malware_Subjects>
        <maecPackage:Malware_Subject id="example:malware_subject-9a70056f-57b0-4588-b007-64f94dac2c16">
            <maecPackage:Malware_Instance_Object_Attributes id="example:Object-6319d4ec-43ef-48fd-9be4-ab7721f34e50">
                <cybox:Properties xsi:type="FileObj:FileObjectType">
                    <FileObj:File_Name>seminor.doc</FileObj:File_Name>
                    <FileObj:Size_In_Bytes>154173</FileObj:Size_In_Bytes>
                    <FileObj:Hashes>
                        <cyboxCommon:Hash>
                            <cyboxCommon:Type xsi:type="cyboxVocabs:HashNameVocab-1.0">MD5</cyboxCommon:Type>
                            <cyboxCommon:Simple_Hash_Value>54CC941747FA99A3521314B9969D4964</cyboxCommon:Simple_Hash_Value>
                        </cyboxCommon:Hash>
                    </FileObj:Hashes>
                </cybox:Properties>
            </maecPackage:Malware_Instance_Object_Attributes>
            <maecPackage:Findings_Bundles>
                <maecPackage:Bundle defined_subject="false" id="example:bundle-4b530b16-30c0-4349-aac1-02a326a3a2e2" schema_version="4.1">
                    <maecBundle:Actions>
                        <maecBundle:Action action_status="success" id="example:action-9f713722-92dd-4a1e-8b24-706a0da02e87">
                            <cybox:Name xsi:type="maecVocabs:FileActionNameVocab-1.0">create file</cybox:Name>
                            <cybox:Associated_Objects>
                                <cybox:Associated_Object id="example:Object-c7685eda-d14e-4f9a-9f01-183715089366"/>
                            </cybox:Associated_Objects>
                        </maecBundle:Action>
                    </maecBundle:Actions>
                </maecPackage:Bundle>
            </maecPackage:Findings_Bundles>
        </maecPackage:Malware_Subject>
    </maecPackage:Malware_Subjects>
</maecPackage:MAEC_Package>
